Metadata-Version: 2.1
Name: topsis-dhruv-102003697
Version: 1.0.0
Summary: A Python package implementing TOPSIS technique.
Home-page: https://github.com/Dhruv23092002/topsisImplementation
Author: Dhruv Singla
Author-email: dhruvsingla2002@gmail.com
License: MIT
Classifier: License :: OSI Approved :: MIT License
Classifier: Programming Language :: Python :: 3
Classifier: Programming Language :: Python :: 3.7
License-File: LICENSE
Requires-Dist: numpy
Requires-Dist: pandas
